combogenius/api/__init__.py
combogenius/api/api.py
combogenius/database/__init__.py
combogenius/database/schema.py
combogenius/database/sql_interactions.py
combogenius/logger/__init__.py
combogenius/logger/logger.py
combogenius/models/__init__.py
combogenius/models/make_combos.py
combogenius-0.2.4.dist-info/LICENSE
combogenius-0.2.4.dist-info/METADATA
combogenius-0.2.4.dist-info/WHEEL
combogenius-0.2.4.dist-info/top_level.txt
combogenius-0.2.4.dist-info/RECORD
