Metadata-Version: 2.1
Name: combogenius
Version: 0.2.4
Summary: A package designed to efficiently generate new product combinations using check information, and deliver combo suggestions to business partners via email.
Author: Anna Movsisyan, Lusine Aghinyan, Ararat Kazarian, Hovhannes Hovhannisyan, Eduard Petrosyan
Classifier: Development Status :: 2 - Pre-Alpha
Classifier: Intended Audience :: Developers
Classifier: License :: OSI Approved :: MIT License
Classifier: Natural Language :: English
Classifier: Programming Language :: Python :: 3
Classifier: Programming Language :: Python :: 3.6
Classifier: Programming Language :: Python :: 3.7
Classifier: Programming Language :: Python :: 3.8
Requires-Python: >=3.6
License-File: LICENSE
